push_tasks/__init__.py
push_tasks/command_line.py
push_tasks/push_tasks.py
proofground_push_tasks-1.0.0.dist-info/LICENSE
proofground_push_tasks-1.0.0.dist-info/METADATA
proofground_push_tasks-1.0.0.dist-info/WHEEL
proofground_push_tasks-1.0.0.dist-info/entry_points.txt
proofground_push_tasks-1.0.0.dist-info/top_level.txt
proofground_push_tasks-1.0.0.dist-info/RECORD
